panflute/__init__.py
panflute/autofilter.py
panflute/base.py
panflute/containers.py
panflute/elements.py
panflute/io.py
panflute/table_elements.py
panflute/tools.py
panflute/utils.py
panflute/version.py
panflute-2.3.1.dist-info/LICENSE
panflute-2.3.1.dist-info/METADATA
panflute-2.3.1.dist-info/WHEEL
panflute-2.3.1.dist-info/entry_points.txt
panflute-2.3.1.dist-info/top_level.txt
panflute-2.3.1.dist-info/RECORD
