Metadata-Version: 2.1
Name: panflute
Version: 2.3.1
Summary: Pythonic Pandoc filters
Home-page: https://github.com/sergiocorreia/panflute
Author: Sergio Correia
Author-email: sergio.correia@gmail.com
License: BSD3
Project-URL: Source, https://github.com/sergiocorreia/panflute
Project-URL: Documentation, http://scorreia.com/software/panflute/
Project-URL: Tracker, https://github.com/sergiocorreia/panflute/issues
Keywords: pandoc pandocfilters markdown latex
Classifier: Development Status :: 5 - Production/Stable
Classifier: Environment :: Console
Classifier: Intended Audience :: End Users/Desktop
Classifier: Intended Audience :: Developers
Classifier: Topic :: Software Development :: Build Tools
Classifier: License :: OSI Approved :: BSD License
Classifier: Operating System :: OS Independent
Classifier: Topic :: Text Processing :: Filters
Classifier: Programming Language :: Python :: 3.7
Classifier: Programming Language :: Python :: 3.8
Classifier: Programming Language :: Python :: 3.9
Classifier: Programming Language :: Python :: 3.10
Classifier: Programming Language :: Python :: 3.11
Classifier: Programming Language :: Python :: Implementation :: CPython
Classifier: Programming Language :: Python :: Implementation :: PyPy
Requires-Python: >=3.7
Provides-Extra: dev
Provides-Extra: pypi
Provides-Extra: extras
License-File: LICENSE
